max734x.py
circuitpython_max734x-0.1.1.dist-info/LICENSE
circuitpython_max734x-0.1.1.dist-info/METADATA
circuitpython_max734x-0.1.1.dist-info/WHEEL
circuitpython_max734x-0.1.1.dist-info/top_level.txt
circuitpython_max734x-0.1.1.dist-info/RECORD
