Metadata-Version: 2.2
Name: circuitpython-max734x
Version: 0.1.1
Summary: CircuitPython driver for MAX7347/MAX7348/MAX7349 keybord and sounder controllers
Author-email: Roman Ondráček <mail@romanondracek.cz>
License: MIT
Project-URL: Homepage, https://github.com/adafruit/Adafruit_CircuitPython_24LC32.git
Keywords: blinka,circuitpython,MAX7347,MAX7348,MAX7349
Classifier: Intended Audience :: Developers
Classifier: Topic :: Software Development :: Libraries
Classifier: Topic :: Software Development :: Embedded Systems
Classifier: Topic :: System :: Hardware
Classifier: License :: OSI Approved :: MIT License
Classifier: Programming Language :: Python :: 3
License-File: LICENSE
Requires-Dist: Adafruit-Blinka
Requires-Dist: adafruit-circuitpython-busdevice
Requires-Dist: adafruit-circuitpython-register
Provides-Extra: optional
Requires-Dist: adafruit-circuitpython-typing; extra == "optional"
Requires-Dist: build; extra == "optional"
